{
	"configurations" : 
	[
		{
			"directories" : 
			[
				{
					"build" : ".",
					"jsonFile" : "directory-.-Debug-f5ebdc15457944623624.json",
					"minimumCMakeVersion" : 
					{
						"string" : "3.6"
					},
					"projectIndex" : 0,
					"source" : ".",
					"targetIndexes" : 
					[
						0,
						1
					]
				}
			],
			"name" : "Debug",
			"projects" : 
			[
				{
					"directoryIndexes" : 
					[
						0
					],
					"name" : "Metronet",
					"targetIndexes" : 
					[
						0,
						1
					]
				}
			],
			"targets" : 
			[
				{
					"directoryIndex" : 0,
					"id" : "main::@6890427a1f51a3e7e1df",
					"jsonFile" : "target-main-Debug-725c98c18d6fb9ecb0b5.json",
					"name" : "main",
					"projectIndex" : 0
				},
				{
					"directoryIndex" : 0,
					"id" : "testing::@6890427a1f51a3e7e1df",
					"jsonFile" : "target-testing-Debug-2e2a2c43d755d95d3c88.json",
					"name" : "testing",
					"projectIndex" : 0
				}
			]
		}
	],
	"kind" : "codemodel",
	"paths" : 
	{
		"build" : "/home/mamadou/CLionProjects/Metronet/cmake-build-debug",
		"source" : "/home/mamadou/CLionProjects/Metronet"
	},
	"version" : 
	{
		"major" : 2,
		"minor" : 4
	}
}
